{
  "dependencies": {
  },
  "providing": {
  },
  "name": "ajain",
  "version": "0.0.1",
  "maintainer_email": "amit.jain@personalcapital.com",
  "attributes": {
    "ajain/apache_package_name": {
      "calculated": false,
      "choice": [

      ],
      "type": "string",
      "display_name": "Apache Package Name",
      "required": "optional",
      "default": "apache2",
      "recipes": [
        "ajain::helloworld"
      ],
      "description": "An override for the apache package name"
    }
  },
  "replacing": {
  },
  "suggestions": {
  },
  "platforms": {
  },
  "license": "All rights reserved",
  "long_description": "Description\n===========\n\nRequirements\n============\n\nAttributes\n==========\n\nUsage\n=====\n\n",
  "conflicting": {
  },
  "recipes": {
    "ajain::create_index": "Put my name",
    "ajain::helloworld": "Prints hello world",
    "ajain::install_foo": "Moves foo.txt to a directory"
  },
  "maintainer": "Personal Capital",
  "description": "Installs/Configures ajain",
  "groupings": {
  },
  "recommendations": {
  }
}